lineagekit/__init__.py
lineagekit/kinship.cpython-312-x86_64-linux-gnu.so
lineagekit/core/AbstractPedigree.py
lineagekit/core/CoalescentTree.py
lineagekit/core/GenGraph.py
lineagekit/core/Pedigree.py
lineagekit/core/PloidPedigree.py
lineagekit/core/__init__.py
lineagekit/core/kinship_core/kinship.cpp
lineagekit/core/kinship_core/parallel_hashmap/btree.h
lineagekit/core/kinship_core/parallel_hashmap/meminfo.h
lineagekit/core/kinship_core/parallel_hashmap/phmap.h
lineagekit/core/kinship_core/parallel_hashmap/phmap_base.h
lineagekit/core/kinship_core/parallel_hashmap/phmap_bits.h
lineagekit/core/kinship_core/parallel_hashmap/phmap_config.h
lineagekit/core/kinship_core/parallel_hashmap/phmap_dump.h
lineagekit/core/kinship_core/parallel_hashmap/phmap_fwd_decl.h
lineagekit/core/kinship_core/parallel_hashmap/phmap_utils.h
lineagekit/core/kinship_core/sparsepp/spp.h
lineagekit/core/kinship_core/sparsepp/spp_config.h
lineagekit/core/kinship_core/sparsepp/spp_dlalloc.h
lineagekit/core/kinship_core/sparsepp/spp_memory.h
lineagekit/core/kinship_core/sparsepp/spp_smartptr.h
lineagekit/core/kinship_core/sparsepp/spp_stdint.h
lineagekit/core/kinship_core/sparsepp/spp_timer.h
lineagekit/core/kinship_core/sparsepp/spp_traits.h
lineagekit/core/kinship_core/sparsepp/spp_utils.h
lineagekit/utility/__init__.py
lineagekit/utility/utility.py
scripts/__init__.py
scripts/ascending_genealogy/__init__.py
scripts/ascending_genealogy/take_ascending_genealogy.py
scripts/ascending_genealogy/take_cartegene_ascending_pedigree.py
scripts/contribution_factor/__init__.py
scripts/contribution_factor/build_contribution_histogram.py
scripts/contribution_factor/calculate_contribution_factors.py
scripts/contribution_factor/select_super_founders.py
scripts/kinship/__init__.py
scripts/kinship/calculate_and_store_kinships.py
scripts/kinship/calculate_kinships.py
scripts/perturb_edges/__init__.py
scripts/perturb_edges/perturb_edges.py
lineagekit-1.0.19.dist-info/METADATA
lineagekit-1.0.19.dist-info/WHEEL
lineagekit-1.0.19.dist-info/top_level.txt
lineagekit-1.0.19.dist-info/RECORD
