Metadata-Version: 2.4
Name: lineagekit
Version: 1.0.19
Summary: A python library with genealogy methods
Requires-Python: >=3.9
Requires-Dist: tskit>=0.5.6
Requires-Dist: networkx>=3.2.1
Requires-Dist: matplotlib>=3.8.3
Requires-Dist: pytest>=8.0.2
Requires-Dist: pandas>=2.0.0
Requires-Dist: numpy>=1.26.4
Requires-Dist: pybind11>=2.12.0
Requires-Dist: setuptools>=78.1.1
Requires-Dist: pip>=24.0
Requires-Dist: attrs>=23.2.0
Requires-Dist: pillow>=10.3.0
Requires-Dist: docutils>=0.20.1
Requires-Dist: Sphinx>=7.2.6
Requires-Dist: sphinx-autodoc-typehints>=1.12.0
Requires-Dist: sphinxcontrib-napoleon>=0.7
Requires-Dist: Jinja2>=3.1.3
Requires-Dist: typing_extensions>=4.10.0
Requires-Dist: pytz>=2024.1
Requires-Dist: Cython>=3.0.10
Requires-Dist: numba>=0.59.1
Requires-Dist: svgwrite>=1.4.3
Requires-Dist: jsonschema>=4.21.1
Requires-Dist: MarkupSafe>=2.1.5
Requires-Dist: python-dateutil>=2.9.0.post0
Requires-Dist: six>=1.16.0
Requires-Dist: referencing>=0.33.0
Requires-Dist: idna>=3.6
Requires-Dist: packaging>=23.2
Requires-Dist: zipp>=3.18.0
Requires-Dist: scipy>=1.13.0
